dcamarcal/__init__.py
dcamarcal/calculator.py
dcamarcal-0.0.1.dist-info/METADATA
dcamarcal-0.0.1.dist-info/WHEEL
dcamarcal-0.0.1.dist-info/licenses/LICENSE
dcamarcal-0.0.1.dist-info/RECORD
