Metadata-Version: 2.3
Name: dcamarcal
Version: 0.0.1
Summary: DCA Martingale strategy calculator.
Project-URL: Homepage, https://github.com/Cobeguel/dcamarcal
Author-email: Cobeguel <cobegueljonsco@gmail.com>
License-Expression: MIT
License-File: LICENSE
Classifier: License :: OSI Approved :: MIT License
Classifier: Operating System :: OS Independent
Classifier: Programming Language :: Python :: 3
Requires-Python: >=3.9
